openai_async_utils/__init__.py
openai_async_utils/text_generation_with_schema_and_retry.py
openai_async_utils-0.1.2.dist-info/licenses/LICENSE
openai_async_utils-0.1.2.dist-info/METADATA
openai_async_utils-0.1.2.dist-info/WHEEL
openai_async_utils-0.1.2.dist-info/top_level.txt
openai_async_utils-0.1.2.dist-info/RECORD
