Metadata-Version: 2.4
Name: openai-async-utils
Version: 0.1.2
Summary: Async helpers for OpenAI chat
Author-email: Mubashir Ahmed Siddiqui <mubashirsidiki@gmail.com>
License: MIT
Keywords: openai,asyncio,utility
License-File: LICENSE
Requires-Dist: openai>=0.27.0
Dynamic: license-file
